platform_agent/__init__.py
platform_agent/__main__.py
platform_agent/agent_api.py
platform_agent/agent_websocket.py
platform_agent/cmd/__init__.py
platform_agent/cmd/lsmod.py
platform_agent/cmd/wg_show.py
platform_agent/config/__init__.py
platform_agent/config/logger.py
platform_agent/config/settings.py
platform_agent/docker_api/__init__.py
platform_agent/docker_api/docker_api.py
platform_agent/docker_api/helpers.py
platform_agent/executors/__init__.py
platform_agent/executors/wg_exec.py
platform_agent/lib/__init__.py
platform_agent/lib/ctime.py
platform_agent/lib/get_info.py
platform_agent/lib/rt_table.py
platform_agent/rerouting/__init__.py
platform_agent/rerouting/rerouting.py
platform_agent/routes/__init__.py
platform_agent/routes/routes.py
platform_agent/wireguard/__init__.py
platform_agent/wireguard/peer_watcher.py
platform_agent/wireguard/wg_conf.py
tests/__init__.py
tests/conftest.py
tests/test_get_info.py
platform_agent_devel-0.0.7.dist-info/METADATA
platform_agent_devel-0.0.7.dist-info/WHEEL
platform_agent_devel-0.0.7.dist-info/entry_points.txt
platform_agent_devel-0.0.7.dist-info/top_level.txt
platform_agent_devel-0.0.7.dist-info/RECORD
