Metadata-Version: 2.1
Name: platform-agent-devel
Version: 0.0.7
Summary: UNKNOWN
Home-page: UNKNOWN
License: MIT
Platform: UNKNOWN
Classifier: License :: OSI Approved :: MIT License
Classifier: Programming Language :: Python :: 3
Classifier: Programming Language :: Python :: 3.8
Requires-Dist: pyroute2 (==0.5.12)
Requires-Dist: websocket-client (==0.57.0)
Requires-Dist: requests (==2.22.0)
Requires-Dist: PyNaCl (==1.3.0)
Requires-Dist: docker-py (==1.10.6)
Requires-Dist: icmplibv2 (==1.0.5)
Requires-Dist: PyYAML (==5.3.1)
